bavaria/__init__.py
bavaria/api/__init__.py
bavaria/api/messages.py
bavaria/exceptions.py
bavaria/feed.py
bavaria/message.py
bavaria/news.py
bavaria/station.py
bavaria-0.1.0.dist-info/LICENSE
bavaria-0.1.0.dist-info/WHEEL
bavaria-0.1.0.dist-info/METADATA
bavaria-0.1.0.dist-info/RECORD
