Metadata-Version: 2.1
Name: bavaria
Version: 0.1.0
Summary: API wrapper for Munich's unoffical S-Bahn websocket API.
Home-page: UNKNOWN
License: MIT
Author: Auke Willem Oosterhoff
Author-email: auke@orangetux.nl
Requires-Python: >=3.7,<4.0
Classifier: License :: OSI Approved :: MIT License
Classifier: Programming Language :: Python :: 3
Classifier: Programming Language :: Python :: 3.7
Requires-Dist: websockets (>=7.0,<8.0)
